structured_data/__init__.py
structured_data/apps.py
structured_data/util.py
structured_data/templatetags/__init__.py
structured_data/templatetags/jsonld.py
structured_data/templatetags/meta.py
structured_data/templatetags/opengraph.py
django_structured_data-0.6.0.dist-info/LICENSE
django_structured_data-0.6.0.dist-info/WHEEL
django_structured_data-0.6.0.dist-info/METADATA
django_structured_data-0.6.0.dist-info/RECORD
