Metadata-Version: 2.1
Name: django-structured-data
Version: 0.6.0
Summary: Template tags to assist in adding structured metadata to views and models.
Home-page: https://github.com/dmptrluke/django-structured-data
Author: Luke Rogers
Author-email: luke@dmptr.com
Requires-Python: >=3.8
Classifier: Programming Language :: Python :: 3
Classifier: Programming Language :: Python :: 3.8
Classifier: Programming Language :: Python :: 3.9
Classifier: Programming Language :: Python :: 3.10
Classifier: Programming Language :: Python :: 3.11
Classifier: Development Status :: 4 - Beta
Classifier: Framework :: Django
Classifier: Intended Audience :: Developers
Classifier: License :: OSI Approved :: MIT License
Classifier: Operating System :: OS Independent
Requires-Dist: django>=3.2
